<annotation>
	<folder></folder>
	<filename>W5_jpg.rf.8ac4994036346ca75709ae9b32fe1346.jpg</filename>
	<path>W5_jpg.rf.8ac4994036346ca75709ae9b32fe1346.jpg</path>
	<source>
		<database>roboflow.ai</database>
	</source>
	<size>
		<width>402</width>
		<height>402</height>
		<depth>3</depth>
	</size>
	<segmented>0</segmented>
	<object>
		<name>W</name>
		<pose>Unspecified</pose>
		<truncated>0</truncated>
		<difficult>0</difficult>
		<occluded>0</occluded>
		<bndbox>
			<xmin>179</xmin>
			<xmax>325</xmax>
			<ymin>135</ymin>
			<ymax>317</ymax>
		</bndbox>
	</object>
</annotation>
